[
  {
    "month": "2025-01",
    "service": "Compute",
    "resource_id": "vm-01",
    "region": "asia-south",
    "usage_type": "on-demand",
    "usage_quantity": 720,
    "unit": "hours",
    "cost_inr": 1200,
    "desc": "Main server"
  },
  {
    "month": "2025-01",
    "service": "Database",
    "resource_id": "db-02",
    "region": "asia-south",
    "usage_type": "on-demand",
    "usage_quantity": 240,
    "unit": "hours",
    "cost_inr": 400,
    "desc": "Database server"
  },
  {
    "month": "2025-01",
    "service": "Object Storage",
    "resource_id": "os-03",
    "region": "asia-south",
    "usage_type": "on-demand",
    "usage_quantity": 960,
    "unit": "hours",
    "cost_inr": 960,
    "desc": "Object storage"
  },
  {
    "month": "2025-01",
    "service": "Monitoring",
    "resource_id": "mon-04",
    "region": "asia-south",
    "usage_type": "on-demand",
    "usage_quantity": 480,
    "unit": "hours",
    "cost_inr": 480,
    "desc": "Monitoring service"
  },
  {
    "month": "2025-01",
    "service": "Analytics",
    "resource_id": "ana-05",
    "region": "asia-south",
    "usage_type": "on-demand",
    "usage_quantity": 240,
    "unit": "hours",
    "cost_inr": 240,
    "desc": "Basic analytics"
  },
  {
    "month": "2025-01",
    "service": "Compute",
    "resource_id": "vm-06",
    "region": "asia-south",
    "usage_type": "on-demand",
    "usage_quantity": 360,
    "unit": "hours",
    "cost_inr": 720,
    "desc": "Load balancer"
  },
  {
    "month": "2025-01",
    "service": "Database",
    "resource_id": "db-07",
    "region": "asia-south",
    "usage_type": "on-demand",
    "usage_quantity": 120,
    "unit": "hours",
    "cost_inr": 160,
    "desc": "Database replica"
  },
  {
    "month": "2025-01",
    "service": "Object Storage",
    "resource_id": "os-08",
    "region": "asia-south",
    "usage_type": "on-demand",
    "usage_quantity": 480,
    "unit": "hours",
    "cost_inr": 480,
    "desc": "Backup storage"
  },
  {
    "month": "2025-01",
    "service": "Monitoring",
    "resource_id": "mon-09",
    "region": "asia-south",
    "usage_type": "on-demand",
    "usage_quantity": 240,
    "unit": "hours",
    "cost_inr": 240,
    "desc": "Monitoring agent"
  },
  {
    "month": "2025-01",
    "service": "Analytics",
    "resource_id": "ana-10",
    "region": "asia-south",
    "usage_type": "on-demand",
    "usage_quantity": 120,
    "unit": "hours",
    "cost_inr": 120,
    "desc": "Data processing"
  },
  {
    "month": "2025-01",
    "service": "Compute",
    "resource_id": "vm-11",
    "region": "asia-south",
    "usage_type": "on-demand",
    "usage_quantity": 240,
    "unit": "hours",
    "cost_inr": 480,
    "desc": "Worker nodes"
  },
  {
    "month": "2025-01",
    "service": "Database",
    "resource_id": "db-12",
    "region": "asia-south",
    "usage_type": "on-demand",
    "usage_quantity": 60,
    "unit": "hours",
    "cost_inr": 80,
    "desc": "Database maintenance"
  },
  {
    "month": "2025-01",
    "service": "Object Storage",
    "resource_id": "os-13",
    "region": "asia-south",
    "usage_type": "on-demand",
    "usage_quantity": 240,
    "unit": "hours",
    "cost_inr": 240,
    "desc": "Data archiving"
  },
  {
    "month": "2025-01",
    "service": "Monitoring",
    "resource_id": "mon-14",
    "region": "asia-south",
    "usage_type": "on-demand",
    "usage_quantity": 120,
    "unit": "hours",
    "cost_inr": 120,
    "desc": "Alerting service"
  },
  {
    "month": "2025-01",
    "service": "Analytics",
    "resource_id": "ana-15",
    "region": "asia-south",
    "usage_type": "on-demand",
    "usage_quantity": 60,
    "unit": "hours",
    "cost_inr": 60,
    "desc": "Data visualization"
  },
  {
    "month": "2025-01",
    "service": "Compute",
    "resource_id": "vm-16",
    "region": "asia-south",
    "usage_type": "on-demand",
    "usage_quantity": 120,
    "unit": "hours",
    "cost_inr": 240,
    "desc": "Development environment"
  },
  {
    "month": "2025-01",
    "service": "Database",
    "resource_id": "db-17",
    "region": "asia-south",
    "usage_type": "on-demand",
    "usage_quantity": 30,
    "unit": "hours",
    "cost_inr": 40,
    "desc": "Database testing"
  },
  {
    "month": "2025-01",
    "service": "Object Storage",
    "resource_id": "os-18",
    "region": "asia-south",
    "usage_type": "on-demand",
    "usage_quantity": 120,
    "unit": "hours",
    "cost_inr": 120,
    "desc": "Data backup"
  },
  {
    "month": "2025-01",
    "service": "Monitoring",
    "resource_id": "mon-19",
    "region": "asia-south",
    "usage_type": "on-demand",
    "usage_quantity": 60,
    "unit": "hours",
    "cost_inr": 60,
    "desc": "Monitoring dashboard"
  },
  {
    "month": "2025-01",
    "service": "Analytics",
    "resource_id": "ana-20",
    "region": "asia-south",
    "usage_type": "on-demand",
    "usage_quantity": 30,
    "unit": "hours",
    "cost_inr": 30,
    "desc": "Data reporting"
  }
]